README.md
pyproject.toml
setup.cfg
src/calculator_813a4904e145b2db/__init__.py
src/calculator_813a4904e145b2db/calculator.py
src/calculator_813a4904e145b2db.egg-info/PKG-INFO
src/calculator_813a4904e145b2db.egg-info/SOURCES.txt
src/calculator_813a4904e145b2db.egg-info/dependency_links.txt
src/calculator_813a4904e145b2db.egg-info/top_level.txt