Metadata-Version: 2.1
Name: calculator-813a4904e145b2db
Version: 0.0.2
Summary: Calculator
Author: Congon4tor
Author-email: congon4tor@justhacking.com
Classifier: Programming Language :: Python :: 3
Classifier: License :: OSI Approved :: MIT License
Classifier: Operating System :: OS Independent
Requires-Python: >=3.6
